{
  "frames": {
    "floor": {
      "frame": {
        "x": 0,
        "y": 0,
        "w": 32,
        "h": 32
      },
      "sourceSize": {
        "w": 32,
        "h": 32
      },
      "spriteSourceSize": {
        "x": 0,
        "y": 0,
        "w": 32,
        "h": 32
      }
    },
    "wall": {
      "frame": {
        "x": 32,
        "y": 0,
        "w": 32,
        "h": 32
      },
      "sourceSize": {
        "w": 32,
        "h": 32
      },
      "spriteSourceSize": {
        "x": 0,
        "y": 0,
        "w": 32,
        "h": 32
      }
    },
    "door": {
      "frame": {
        "x": 64,
        "y": 0,
        "w": 32,
        "h": 32
      },
      "sourceSize": {
        "w": 32,
        "h": 32
      },
      "spriteSourceSize": {
        "x": 0,
        "y": 0,
        "w": 32,
        "h": 32
      }
    },
    "player": {
      "frame": {
        "x": 0,
        "y": 32,
        "w": 32,
        "h": 32
      },
      "sourceSize": {
        "w": 32,
        "h": 32
      },
      "spriteSourceSize": {
        "x": 0,
        "y": 0,
        "w": 32,
        "h": 32
      }
    },
    "enemy_triangle": {
      "frame": {
        "x": 32,
        "y": 32,
        "w": 32,
        "h": 32
      },
      "sourceSize": {
        "w": 32,
        "h": 32
      },
      "spriteSourceSize": {
        "x": 0,
        "y": 0,
        "w": 32,
        "h": 32
      }
    },
    "enemy_square": {
      "frame": {
        "x": 64,
        "y": 32,
        "w": 32,
        "h": 32
      },
      "sourceSize": {
        "w": 32,
        "h": 32
      },
      "spriteSourceSize": {
        "x": 0,
        "y": 0,
        "w": 32,
        "h": 32
      }
    },
    "item_potion": {
      "frame": {
        "x": 0,
        "y": 64,
        "w": 32,
        "h": 32
      },
      "sourceSize": {
        "w": 32,
        "h": 32
      },
      "spriteSourceSize": {
        "x": 0,
        "y": 0,
        "w": 32,
        "h": 32
      }
    },
    "item_star": {
      "frame": {
        "x": 32,
        "y": 64,
        "w": 32,
        "h": 32
      },
      "sourceSize": {
        "w": 32,
        "h": 32
      },
      "spriteSourceSize": {
        "x": 0,
        "y": 0,
        "w": 32,
        "h": 32
      }
    }
  },
  "meta": {
    "image": "tileset.png",
    "format": "RGBA8888",
    "size": {
      "w": 128,
      "h": 128
    },
    "scale": 1
  }
}